django_forge-0.7.1.dist-info/DESCRIPTION.rst
django_forge-0.7.1.dist-info/METADATA
django_forge-0.7.1.dist-info/metadata.json
django_forge-0.7.1.dist-info/RECORD
django_forge-0.7.1.dist-info/top_level.txt
django_forge-0.7.1.dist-info/WHEEL
forge/__init__.py
forge/admin.py
forge/client.py
forge/constants.py
forge/dependency.py
forge/models.py
forge/semver.py
forge/storage.py
forge/urls.py
forge/management/__init__.py
forge/management/commands/__init__.py
forge/management/commands/sync_forge.py
forge/settings/__init__.py
forge/settings/base.py
forge/settings/dev.py
forge/settings/key.py
forge/settings/prod.py
forge/settings/secret_key.py
forge/templates/admin/base_site.html
forge/tests/__init__.py
forge/tests/test_modules_v1.py
forge/tests/test_releases_v1.py
forge/tests/test_semver.py
forge/views/__init__.py
forge/views/static.py
forge/views/utils.py
forge/views/v1.py
forge/views/v3.py
