Metadata-Version: 2.0
Name: django-forge
Version: 0.7.1
Summary: A Django implementation of the Puppet Forge API.
Home-page: https://github.com/jbronn/django-forge
Author: Justin Bronn
Author-email: jbronn@gmail.com
License: UNKNOWN
Download-URL: http://pypi.python.org/pypi/django-forge/
Platform: UNKNOWN
Classifier: Development Status :: 4 - Beta
Classifier: Environment :: Web Environment
Classifier: Framework :: Django
Classifier: Intended Audience :: Developers
Classifier: Intended Audience :: System Administrators
Classifier: License :: OSI Approved :: Apache Software License
Requires-Dist: Django (>=1.8)
Requires-Dist: requests (>=2)
Requires-Dist: semantic-version (>=2.1.2)
